gmg/__init__.py
gmg/const.py
gmg/core.py
gmg-0.0.4.dist-info/LICENSE
gmg-0.0.4.dist-info/METADATA
gmg-0.0.4.dist-info/WHEEL
gmg-0.0.4.dist-info/top_level.txt
gmg-0.0.4.dist-info/RECORD
