Metadata-Version: 2.1
Name: gmg
Version: 0.0.4
Summary: Middleware for talking to your Green Mountain Grill
Home-page: UNKNOWN
Author: Christopher McKay
Author-email: mckaycr@gmail.com
License: MIT
Platform: UNKNOWN
